chunkr_ai/__init__.py
chunkr_ai/models.py
chunkr_ai/api/__init__.py
chunkr_ai/api/auth.py
chunkr_ai/api/chunkr.py
chunkr_ai/api/chunkr_base.py
chunkr_ai/api/configuration.py
chunkr_ai/api/decorators.py
chunkr_ai/api/misc.py
chunkr_ai/api/protocol.py
chunkr_ai/api/task_response.py
chunkr_ai-0.3.6.dist-info/licenses/LICENSE
chunkr_ai-0.3.6.dist-info/METADATA
chunkr_ai-0.3.6.dist-info/WHEEL
chunkr_ai-0.3.6.dist-info/top_level.txt
chunkr_ai-0.3.6.dist-info/RECORD
