Metadata-Version: 2.4
Name: chunkr-ai
Version: 0.3.6
Summary: Python client for Chunkr: open source document intelligence
Author-email: Ishaan Kapoor <ishaan@lumina.sh>
License: MIT License
Project-URL: Homepage, https://chunkr.ai
Requires-Python: >=3.10
License-File: LICENSE
Requires-Dist: httpx>=0.25.0
Requires-Dist: nest-asyncio>=1.6.0
Requires-Dist: pillow>=10.0.0
Requires-Dist: pydantic>=2.0.0
Requires-Dist: python-dotenv>=0.19.0
Requires-Dist: tomli>=1.2.0; python_version < "3.11"
Provides-Extra: test
Requires-Dist: pytest>=7.0.0; extra == "test"
Requires-Dist: pytest-xdist>=3.0.0; extra == "test"
Requires-Dist: pytest-asyncio>=0.21.0; extra == "test"
Requires-Dist: ruff>=0.9.3; extra == "test"
Requires-Dist: matplotlib>=3.10.3; extra == "test"
Dynamic: license-file
